scdistill/__init__.py
scdistill/distiller.py
scdistill/model.py
scdistill/subsampling.py
scdistill/de/__init__.py
scdistill/de/differential_expression.py
scdistill/evaluation/__init__.py
scdistill/evaluation/covariate.py
scdistill/evaluation/metrics.py
scdistill/nn/__init__.py
scdistill/nn/distillation.py
scdistill/nn/zinb.py
scdistill/teachers/__init__.py
scdistill/teachers/base.py
scdistill/teachers/combat.py
scdistill/teachers/fastmnn.py
scdistill/teachers/harmony.py
scdistill/teachers/liger.py
scdistill/teachers/scanorama.py
scdistill/teachers/symphony.py
scdistill-0.2.0.dist-info/METADATA
scdistill-0.2.0.dist-info/WHEEL
scdistill-0.2.0.dist-info/licenses/LICENSE
scdistill-0.2.0.dist-info/RECORD
